moonrise/Base_Test.py
moonrise/Moon_Browser.py
moonrise/Moon_Methods.py
moonrise/Moon_Movie.py
moonrise/__init__.py
moonrise/__main__.py
moonrise-1.1.7.dist-info/LICENSE
moonrise-1.1.7.dist-info/METADATA
moonrise-1.1.7.dist-info/WHEEL
moonrise-1.1.7.dist-info/entry_points.txt
moonrise-1.1.7.dist-info/top_level.txt
moonrise-1.1.7.dist-info/RECORD
