Metadata-Version: 2.1
Name: moonrise
Version: 1.1.7
Summary: Test suite creation toolset with additional quality of life upgrades for using the selenium test framework.
Home-page: https://github.com/Worakow1138/Moonrise
Author: Christopher Diamond-Jones
Author-email: christopher.jones1138@gmail.com
License: MIT License
Classifier: Programming Language :: Python :: 3
Classifier: License :: OSI Approved :: MIT License
Classifier: Operating System :: OS Independent
Requires-Python: >=3.7
License-File: LICENSE
Requires-Dist: selenium
Requires-Dist: colorama
Requires-Dist: ffmpeg-python
